{
  "promo": [{
      "id": 1,
      "images": "https://firebasestorage.googleapis.com/v0/b/test-e8170.appspot.com/o/product.png?alt=media&token=c4f3acf6-8347-42c6-bb33-ce6b7673518f",
      "alt": "promotion",
      "title": "Colombia Supremo",
      "subtitle": {
        "ru": "Свежеобжаренный кофе - описание товара, вкус, аромат",
        "en": "Freshly roasted coffee - product description, taste, aroma"
      },
      "oldPrice": 350,
      "price": 250,
      "sourness": 7,
      "peppercorn": 7,
      "saturation": 7,
      "rating": 3.0,
      "review": 32,
      "stars": 3,
      "gram": 250,
      "grains": 5
    },
    {
      "id": 2,
      "images": "https://firebasestorage.googleapis.com/v0/b/test-e8170.appspot.com/o/product.png?alt=media&token=c4f3acf6-8347-42c6-bb33-ce6b7673518f",
      "alt": "promotion",
      "title": "Colombia Supremo",
      "subtitle": {
        "ru": "Свежеобжаренный кофе - описание товара, вкус, аромат",
        "en": "Freshly roasted coffee - product description, taste, aroma"
      },
      "oldPrice": 350,
      "price": 250,
      "sourness": 7,
      "peppercorn": 7,
      "saturation": 7,
      "rating": 5.0,
      "review": 32,
      "stars": 5,
      "gram": 250,
      "grains": 5
    },
    {
      "id": 3,
      "images": "https://firebasestorage.googleapis.com/v0/b/test-e8170.appspot.com/o/product.png?alt=media&token=c4f3acf6-8347-42c6-bb33-ce6b7673518f",
      "alt": "promotion",
      "title": "Colombia Supremo",
      "subtitle": {
        "ru": "Свежеобжаренный кофе - описание товара, вкус, аромат",
        "en": "Freshly roasted coffee - product description, taste, aroma"
      },
      "oldPrice": 350,
      "price": 250,
      "sourness": 7,
      "peppercorn": 7,
      "saturation": 7,
      "rating": 3.0,
      "review": 32,
      "stars": 3,
      "gram": 250,
      "grains": 5
    },
    {
      "id": 4,
      "images": "https://firebasestorage.googleapis.com/v0/b/test-e8170.appspot.com/o/product.png?alt=media&token=c4f3acf6-8347-42c6-bb33-ce6b7673518f",
      "alt": "promotion",
      "title": "Colombia Supremo",
      "subtitle": {
        "ru": "Свежеобжаренный кофе - описание товара, вкус, аромат",
        "en": "Freshly roasted coffee - product description, taste, aroma"
      },
      "oldPrice": 350,
      "price": 250,
      "sourness": 7,
      "peppercorn": 7,
      "saturation": 7,
      "rating": 1.0,
      "review": 32,
      "stars": 1,
      "gram": 250,
      "grains": 5
    },
    {
      "id": 5,
      "images": "https://firebasestorage.googleapis.com/v0/b/test-e8170.appspot.com/o/product.png?alt=media&token=c4f3acf6-8347-42c6-bb33-ce6b7673518f",
      "alt": "promotion",
      "title": "Colombia Supremo",
      "subtitle": {
        "ru": "Свежеобжаренный кофе - описание товара, вкус, аромат",
        "en": "Freshly roasted coffee - product description, taste, aroma"
      },
      "oldPrice": 350,
      "price": 250,
      "sourness": 7,
      "peppercorn": 7,
      "saturation": 7,
      "rating": 5.0,
      "review": 32,
      "stars": 5,
      "gram": 250,
      "grains": 5
    },
    {
      "id": 6,
      "images": "https://firebasestorage.googleapis.com/v0/b/test-e8170.appspot.com/o/product.png?alt=media&token=c4f3acf6-8347-42c6-bb33-ce6b7673518f",
      "alt": "promotion",
      "title": "Colombia Supremo",
      "subtitle": {
        "ru": "Свежеобжаренный кофе - описание товара, вкус, аромат",
        "en": "Freshly roasted coffee - product description, taste, aroma"
      },
      "oldPrice": 350,
      "price": 250,
      "sourness": 7,
      "peppercorn": 7,
      "saturation": 7,
      "rating": 4.0,
      "review": 32,
      "stars": 4,
      "gram": 250,
      "grains": 5
    }
  ]
}
